nlcc/__init__.py
nlcc/eval.py
nlcc/hf.py
nlcc/hf_local.py
nlcc/incoder.py
nlcc/lib.py
nlcc/main.py
nlcc/nlp.py
nlcc/openai.py
nlcc/prompt.py
nlcc/timeout.py
nlcc/version.py
nlcc/prompts/md-prompts.yml
nlcc/prompts/py-prompts.yml
nlcc/prompts/sh-prompts.yml
nlcc-0.6.0.dist-info/METADATA
nlcc-0.6.0.dist-info/WHEEL
nlcc-0.6.0.dist-info/entry_points.txt
nlcc-0.6.0.dist-info/top_level.txt
nlcc-0.6.0.dist-info/zip-safe
nlcc-0.6.0.dist-info/RECORD
