Metadata-Version: 2.1
Name: nlcc
Version: 0.6.0
Summary: Natural language computational chemistry
Home-page: https://github.com/whitead/nlcc
Author: Andrew & Frank
Author-email: andrew.white@rochester.edu
License: MIT
Classifier: Programming Language :: Python :: 3
Classifier: License :: OSI Approved :: MIT License
Classifier: Operating System :: OS Independent
Classifier: Topic :: Scientific/Engineering :: Bio-Informatics
Classifier: Topic :: Scientific/Engineering :: Chemistry
Classifier: Topic :: Scientific/Engineering :: Artificial Intelligence
Requires-Dist: click
Requires-Dist: importlib-resources
Requires-Dist: importlib-metadata
Requires-Dist: numpy
Requires-Dist: pyyaml
Requires-Dist: openai
Requires-Dist: pyperclip
Requires-Dist: prompt-toolkit
Requires-Dist: tabulate
Requires-Dist: pyrate-limiter
Requires-Dist: rich
